parallel_ml/__init__.py
parallel_ml/_defaults.py
parallel_ml/data.py
parallel_ml/interpret.py
parallel_ml/mask_generation.py
parallel_ml/metrics.py
parallel_ml/multiprocessing.py
parallel_ml/train.py
parallel_ml-0.0.1.dist-info/LICENSE
parallel_ml-0.0.1.dist-info/METADATA
parallel_ml-0.0.1.dist-info/WHEEL
parallel_ml-0.0.1.dist-info/top_level.txt
parallel_ml-0.0.1.dist-info/RECORD
